exapi_client_python/__init__.py
exapi_client_python/api_client.py
exapi_client_python/api_response.py
exapi_client_python/configuration.py
exapi_client_python/exceptions.py
exapi_client_python/py.typed
exapi_client_python/rest.py
exapi_client_python/api/__init__.py
exapi_client_python/api/account_api.py
exapi_client_python/api/pool_api.py
exapi_client_python/api/public_api.py
exapi_client_python/api/trade_api.py
exapi_client_python/models/__init__.py
exapi_client_python/models/private_balances_get200_response.py
exapi_client_python/models/private_deposit_address_get200_response.py
exapi_client_python/models/private_deposits_get200_response_inner.py
exapi_client_python/models/private_orders_cancel_post_request.py
exapi_client_python/models/private_orders_get200_response_inner.py
exapi_client_python/models/private_orders_get200_response_inner_fee.py
exapi_client_python/models/private_orders_post_request.py
exapi_client_python/models/private_pool_join_post200_response.py
exapi_client_python/models/private_pool_join_post_request.py
exapi_client_python/models/private_pool_leave_post_request.py
exapi_client_python/models/private_pool_tasks_get200_response_inner.py
exapi_client_python/models/private_pool_tasks_get200_response_inner_spent_inner.py
exapi_client_python/models/private_trades_get200_response_inner.py
exapi_client_python/models/private_withdrawals_detail_get200_response.py
exapi_client_python/models/private_withdrawals_finish_post200_response.py
exapi_client_python/models/private_withdrawals_finish_post_request.py
exapi_client_python/models/private_withdrawals_prepare_post200_response.py
exapi_client_python/models/private_withdrawals_prepare_post_request.py
exapi_client_python/models/public_currencies_get200_response_inner.py
exapi_client_python/models/public_currencies_get200_response_inner_networks_inner.py
exapi_client_python/models/public_currencies_get_default_response.py
exapi_client_python/models/public_exk_config_get200_response.py
exapi_client_python-2.4.1.dist-info/METADATA
exapi_client_python-2.4.1.dist-info/WHEEL
exapi_client_python-2.4.1.dist-info/top_level.txt
exapi_client_python-2.4.1.dist-info/RECORD
