Metadata-Version: 2.1
Name: exapi-client-python
Version: 2.4.1
Summary: ExKoin API Documentation
Home-page: 
Author: OpenAPI Generator community
Author-email: team@openapitools.org
Keywords: OpenAPI,OpenAPI-Generator,ExKoin API Documentation
Requires-Dist: pydantic (>=2)
Requires-Dist: python-dateutil (>=2.8.2)
Requires-Dist: typing-extensions (>=4.7.1)
Requires-Dist: urllib3 (<3.0.0,>=2.1.0)
